prefixed/__init__.py
prefixed-0.8.0.dist-info/LICENSE
prefixed-0.8.0.dist-info/METADATA
prefixed-0.8.0.dist-info/WHEEL
prefixed-0.8.0.dist-info/top_level.txt
prefixed-0.8.0.dist-info/RECORD
