Metadata-Version: 2.1
Name: prefixed
Version: 0.8.0
Summary: Prefixed alternative numeric library
Home-page: https://github.com/Rockhopper-Technologies/prefixed
Author: Avram Lubkin
Author-email: avylove@rockhopper.net
Maintainer: Avram Lubkin
Maintainer-email: avylove@rockhopper.net
License: MPLv2.0
Project-URL: Documentation, https://prefixed.readthedocs.io
Keywords: si iec prefix nist
Classifier: Development Status :: 4 - Beta
Classifier: Intended Audience :: Developers
Classifier: License :: OSI Approved :: Mozilla Public License 2.0 (MPL 2.0)
Classifier: Operating System :: POSIX
Classifier: Operating System :: Microsoft :: Windows
Classifier: Programming Language :: Python
Classifier: Programming Language :: Python :: 2.7
Classifier: Programming Language :: Python :: 3.5
Classifier: Programming Language :: Python :: 3.6
Classifier: Programming Language :: Python :: 3.7
Classifier: Programming Language :: Python :: 3.8
Classifier: Programming Language :: Python :: 3.9
Classifier: Programming Language :: Python :: 3.10
Classifier: Programming Language :: Python :: 3.11
Classifier: Programming Language :: Python :: 3.12
Classifier: Programming Language :: Python :: 3.13
Classifier: Programming Language :: Python :: Implementation :: CPython
Classifier: Programming Language :: Python :: Implementation :: PyPy
Classifier: Topic :: Terminals
License-File: LICENSE
